[
    {
        "idcorredor": "1",
        "nombre":"Juan Manuel Garcia",
        "fecha_nacimiento":"2004-03-12"
        
    },
    {
        "idcorredor": "2",
        "nombre":"Pedro Garcia",
        "fecha_nacimiento":"2002-01-25"
    },
    {
        "idcorredor": "3",
        "nombre":"Borja Frances",
        "fecha_nacimiento":"2001-12-30"
    },
    {
        "idcorredor": "4",
        "nombre":"Carlos Juan",
        "fecha_nacimiento":"1997-06-28"
    },
    {
        "idcorredor": "5",
        "nombre":"Angel Martinez",
        "fecha_nacimiento":"1996-12-11"
    },
    {
        "idcorredor": "6",
        "nombre":"Paco Garcia",
        "fecha_nacimiento":"1990-05-28"
    },
    {
        "idcorredor": "7",
        "nombre":"Francisco Estevan",
        "fecha_nacimiento":"1990-08-18"
    },
    {
        "idcorredor": "8",
        "nombre":"Antonio Prats",
        "fecha_nacimiento":"1979-03-29"
    },
    {
        "idcorredor": "9",
        "nombre":"Jose Navarro",
        "fecha_nacimiento":"1978-02-03"
    },
    {
        "idcorredor": "10",
        "nombre":"Juan Antonio Garcia",
        "fecha_nacimiento":"1990-10-15"
    }

]